GDO_Email/GDOTools.py
GDO_Email/__init__.py
GDO_Email-0.1.0.dist-info/METADATA
GDO_Email-0.1.0.dist-info/WHEEL
GDO_Email-0.1.0.dist-info/top_level.txt
GDO_Email-0.1.0.dist-info/RECORD
