Metadata-Version: 2.1
Name: GDO-Email
Version: 0.1.0
Summary: • Script To Check Email .
Home-page: https://github.com/GDOTools/GDO-Email
Author: GDOTools
Author-email: GDOTools@gmail.com
Project-URL: Bug Tracker, https://github.com/pypa/sampleproject/issues
Classifier: Programming Language :: Python :: 3
Classifier: License :: OSI Approved :: MIT License
Classifier: Operating System :: OS Independent
Requires-Python: >=3.9
